project_eden/__init__.py
project_eden/cli.py
project_eden/db/__init__.py
project_eden/db/company_tickers.json
project_eden/db/config_example.json
project_eden/db/create_db_from_local_csv.py
project_eden/db/create_tables.py
project_eden/db/data_ingestor.py
project_eden/db/failed_quarter_symbols.txt
project_eden/db/portfolio_tickers.txt
project_eden/db/utils.py
project_eden-0.1.0.dist-info/entry_points.txt
project_eden-0.1.0.dist-info/LICENSE
project_eden-0.1.0.dist-info/METADATA
project_eden-0.1.0.dist-info/WHEEL
project_eden-0.1.0.dist-info/RECORD
