Metadata-Version: 2.1
Name: project-eden
Version: 0.1.0
Summary: Project Eden is a fundamental analysis engine, empowering investors to make smarter investment decisions.
License: AGPL-3.0
Author: glabaria
Author-email: george[DOT]labaria[AT]gmail[DOT]com
Requires-Python: >=3.12,<4.0
Classifier: License :: OSI Approved :: GNU Affero General Public License v3
Classifier: Programming Language :: Python :: 3
Classifier: Programming Language :: Python :: 3.12
Classifier: Programming Language :: Python :: 3.13
Requires-Dist: click (>=8.1.8,<9.0.0)
